pixel_patrol_image/plugin_registry.py
pixel_patrol_image/plugins/processors/quality_metrics_processor.py
pixel_patrol_image/plugins/widgets/dynamic_quality_metrics.py
pixel_patrol_image/plugins/widgets/image_quality.py
pixel_patrol_image-0.1.2.dist-info/METADATA
pixel_patrol_image-0.1.2.dist-info/WHEEL
pixel_patrol_image-0.1.2.dist-info/entry_points.txt
pixel_patrol_image-0.1.2.dist-info/top_level.txt
pixel_patrol_image-0.1.2.dist-info/RECORD
