Metadata-Version: 2.4
Name: pixel-patrol-image
Version: 0.1.2
Summary: Image prevalidation tool
Requires-Python: >=3.11
Requires-Dist: pixel-patrol-base==0.1.2
Requires-Dist: opencv-python-headless>=4.8
